{
  "data": [
    {
      "id": 1,
      "attributes": {
        "productName": "Canasto para la ropa",
        "stock": 23,
        "productDescription": "  CANASTO PARA ROPA JUGUETES, CON TAPA • Diseño ratán  • Cómodo y estético     • Excelente calidad y terminación   • Tamaño: Arriba 57.5cm de alto 42cm de ancho x 32.5cm de profundidad  Base 32cm x 23cm • Capacidad 65L ",
        "productCode": "125",
        "wholesalePrice": 850,
        "retailPrice": 251,
        "isActive": true,
        "uidProduct": "canasto-para-la-ropa",
        "createdAt": "2023-12-25T19:04:18.298Z",
        "updatedAt": "2024-01-03T21:24:52.282Z",
        "publishedAt": "2023-12-25T19:08:28.884Z",
        "closedBox": 12,
        "productPhoto": {
          "data": [
            {
              "id": 1,
              "attributes": {
                "name": "PUBLICACION CANASTO PARA ROPA.png",
                "alternativeText": null,
                "caption": null,
                "width": 1080,
                "height": 1080,
                "formats": {
                  "large": {
                    "ext": ".png",
                    "url": "https://res.cloudinary.com/dalnvh4rx/image/upload/v1703532221/large_PUBLICACION_CANASTO_PARA_ROPA_c9e6586bde.png",
                    "hash": "large_PUBLICACION_CANASTO_PARA_ROPA_c9e6586bde",
                    "mime": "image/png",
                    "name": "large_PUBLICACION CANASTO PARA ROPA.png",
                    "path": null,
                    "size": 399.39,
                    "width": 1000,
                    "height": 1000,
                    "provider_metadata": {
                      "public_id": "large_PUBLICACION_CANASTO_PARA_ROPA_c9e6586bde",
                      "resource_type": "image"
                    }
                  },
                  "small": {
                    "ext": ".png",
                    "url": "https://res.cloudinary.com/dalnvh4rx/image/upload/v1703532220/small_PUBLICACION_CANASTO_PARA_ROPA_c9e6586bde.png",
                    "hash": "small_PUBLICACION_CANASTO_PARA_ROPA_c9e6586bde",
                    "mime": "image/png",
                    "name": "small_PUBLICACION CANASTO PARA ROPA.png",
                    "path": null,
                    "size": 136.38,
                    "width": 500,
                    "height": 500,
                    "provider_metadata": {
                      "public_id": "small_PUBLICACION_CANASTO_PARA_ROPA_c9e6586bde",
                      "resource_type": "image"
                    }
                  },
                  "medium": {
                    "ext": ".png",
                    "url": "https://res.cloudinary.com/dalnvh4rx/image/upload/v1703532221/medium_PUBLICACION_CANASTO_PARA_ROPA_c9e6586bde.png",
                    "hash": "medium_PUBLICACION_CANASTO_PARA_ROPA_c9e6586bde",
                    "mime": "image/png",
                    "name": "medium_PUBLICACION CANASTO PARA ROPA.png",
                    "path": null,
                    "size": 256.27,
                    "width": 750,
                    "height": 750,
                    "provider_metadata": {
                      "public_id": "medium_PUBLICACION_CANASTO_PARA_ROPA_c9e6586bde",
                      "resource_type": "image"
                    }
                  },
                  "thumbnail": {
                    "ext": ".png",
                    "url": "https://res.cloudinary.com/dalnvh4rx/image/upload/v1703532220/thumbnail_PUBLICACION_CANASTO_PARA_ROPA_c9e6586bde.png",
                    "hash": "thumbnail_PUBLICACION_CANASTO_PARA_ROPA_c9e6586bde",
                    "mime": "image/png",
                    "name": "thumbnail_PUBLICACION CANASTO PARA ROPA.png",
                    "path": null,
                    "size": 22.04,
                    "width": 156,
                    "height": 156,
                    "provider_metadata": {
                      "public_id": "thumbnail_PUBLICACION_CANASTO_PARA_ROPA_c9e6586bde",
                      "resource_type": "image"
                    }
                  }
                },
                "hash": "PUBLICACION_CANASTO_PARA_ROPA_c9e6586bde",
                "ext": ".png",
                "mime": "image/png",
                "size": 110.12,
                "url": "https://res.cloudinary.com/dalnvh4rx/image/upload/v1703532220/PUBLICACION_CANASTO_PARA_ROPA_c9e6586bde.png",
                "previewUrl": null,
                "provider": "cloudinary",
                "provider_metadata": {
                  "public_id": "PUBLICACION_CANASTO_PARA_ROPA_c9e6586bde",
                  "resource_type": "image"
                },
                "createdAt": "2023-12-25T19:23:40.157Z",
                "updatedAt": "2023-12-25T19:23:40.157Z"
              }
            },
            {
              "id": 2,
              "attributes": {
                "name": "PUBLICACION CANASTO PARA ROPA.png",
                "alternativeText": null,
                "caption": null,
                "width": 1080,
                "height": 1080,
                "formats": {
                  "large": {
                    "ext": ".png",
                    "url": "https://res.cloudinary.com/dalnvh4rx/image/upload/v1703532224/large_PUBLICACION_CANASTO_PARA_ROPA_d0716b3e65.png",
                    "hash": "large_PUBLICACION_CANASTO_PARA_ROPA_d0716b3e65",
                    "mime": "image/png",
                    "name": "large_PUBLICACION CANASTO PARA ROPA.png",
                    "path": null,
                    "size": 399.39,
                    "width": 1000,
                    "height": 1000,
                    "provider_metadata": {
                      "public_id": "large_PUBLICACION_CANASTO_PARA_ROPA_d0716b3e65",
                      "resource_type": "image"
                    }
                  },
                  "small": {
                    "ext": ".png",
                    "url": "https://res.cloudinary.com/dalnvh4rx/image/upload/v1703532223/small_PUBLICACION_CANASTO_PARA_ROPA_d0716b3e65.png",
                    "hash": "small_PUBLICACION_CANASTO_PARA_ROPA_d0716b3e65",
                    "mime": "image/png",
                    "name": "small_PUBLICACION CANASTO PARA ROPA.png",
                    "path": null,
                    "size": 136.38,
                    "width": 500,
                    "height": 500,
                    "provider_metadata": {
                      "public_id": "small_PUBLICACION_CANASTO_PARA_ROPA_d0716b3e65",
                      "resource_type": "image"
                    }
                  },
                  "medium": {
                    "ext": ".png",
                    "url": "https://res.cloudinary.com/dalnvh4rx/image/upload/v1703532224/medium_PUBLICACION_CANASTO_PARA_ROPA_d0716b3e65.png",
                    "hash": "medium_PUBLICACION_CANASTO_PARA_ROPA_d0716b3e65",
                    "mime": "image/png",
                    "name": "medium_PUBLICACION CANASTO PARA ROPA.png",
                    "path": null,
                    "size": 256.27,
                    "width": 750,
                    "height": 750,
                    "provider_metadata": {
                      "public_id": "medium_PUBLICACION_CANASTO_PARA_ROPA_d0716b3e65",
                      "resource_type": "image"
                    }
                  },
                  "thumbnail": {
                    "ext": ".png",
                    "url": "https://res.cloudinary.com/dalnvh4rx/image/upload/v1703532222/thumbnail_PUBLICACION_CANASTO_PARA_ROPA_d0716b3e65.png",
                    "hash": "thumbnail_PUBLICACION_CANASTO_PARA_ROPA_d0716b3e65",
                    "mime": "image/png",
                    "name": "thumbnail_PUBLICACION CANASTO PARA ROPA.png",
                    "path": null,
                    "size": 22.04,
                    "width": 156,
                    "height": 156,
                    "provider_metadata": {
                      "public_id": "thumbnail_PUBLICACION_CANASTO_PARA_ROPA_d0716b3e65",
                      "resource_type": "image"
                    }
                  }
                },
                "hash": "PUBLICACION_CANASTO_PARA_ROPA_d0716b3e65",
                "ext": ".png",
                "mime": "image/png",
                "size": 110.12,
                "url": "https://res.cloudinary.com/dalnvh4rx/image/upload/v1703532223/PUBLICACION_CANASTO_PARA_ROPA_d0716b3e65.png",
                "previewUrl": null,
                "provider": "cloudinary",
                "provider_metadata": {
                  "public_id": "PUBLICACION_CANASTO_PARA_ROPA_d0716b3e65",
                  "resource_type": "image"
                },
                "createdAt": "2023-12-25T19:23:42.936Z",
                "updatedAt": "2023-12-25T19:23:42.936Z"
              }
            }
          ]
        },
        "categories": {
          "data": [
            {
              "id": 1,
              "attributes": {
                "name": "Plasticos",
                "createdAt": "2023-12-23T18:07:59.587Z",
                "updatedAt": "2023-12-25T17:37:35.287Z",
                "publishedAt": "2023-12-25T17:37:35.284Z"
              }
            },
            {
              "id": 3,
              "attributes": {
                "name": "Jardín y Hogar",
                "createdAt": "2023-12-25T17:37:47.910Z",
                "updatedAt": "2023-12-25T17:37:48.590Z",
                "publishedAt": "2023-12-25T17:37:48.587Z"
              }
            }
          ]
        }
      }
    },
    {
      "id": 4,
      "attributes": {
        "productName": "caja de zapatos",
        "stock": 234,
        "productDescription": "Presentamos nuestra elegante caja de zapatos premium, fabricada con materiales de alta calidad para garantizar durabilidad y estilo. Con dimensiones de 30 cm x 20 cm x 10 cm, esta caja es perfecta para almacenar y proteger tus zapatos favoritos. El exterior de la caja presenta un diseño moderno en color negro mate, mientras que el interior cuenta con un suave forro de terciopelo gris para mantener tus zapatos en perfecto estado. La tapa magnética añade un toque de sofisticación y facilita el acceso a tus calzados. ¡Ordena ahora y dale a tus zapatos el hogar que se merecen!",
        "productCode": "1253",
        "wholesalePrice": 352,
        "retailPrice": 680,
        "isActive": true,
        "uidProduct": "caja",
        "createdAt": "2023-12-31T19:48:08.422Z",
        "updatedAt": "2024-01-03T21:25:40.053Z",
        "publishedAt": "2023-12-31T19:48:08.417Z",
        "closedBox": 10,
        "productPhoto": {
          "data": [
            {
              "id": 5,
              "attributes": {
                "name": "DESTACADA productos.png",
                "alternativeText": null,
                "caption": null,
                "width": 1080,
                "height": 1080,
                "formats": {
                  "large": {
                    "ext": ".png",
                    "url": "https://res.cloudinary.com/dalnvh4rx/image/upload/v1704052090/large_DESTACADA_productos_ac46b233c5.png",
                    "hash": "large_DESTACADA_productos_ac46b233c5",
                    "mime": "image/png",
                    "name": "large_DESTACADA productos.png",
                    "path": null,
                    "size": 23.78,
                    "width": 1000,
                    "height": 1000,
                    "provider_metadata": {
                      "public_id": "large_DESTACADA_productos_ac46b233c5",
                      "resource_type": "image"
                    }
                  },
                  "small": {
                    "ext": ".png",
                    "url": "https://res.cloudinary.com/dalnvh4rx/image/upload/v1704052090/small_DESTACADA_productos_ac46b233c5.png",
                    "hash": "small_DESTACADA_productos_ac46b233c5",
                    "mime": "image/png",
                    "name": "small_DESTACADA productos.png",
                    "path": null,
                    "size": 10.07,
                    "width": 500,
                    "height": 500,
                    "provider_metadata": {
                      "public_id": "small_DESTACADA_productos_ac46b233c5",
                      "resource_type": "image"
                    }
                  },
                  "medium": {
                    "ext": ".png",
                    "url": "https://res.cloudinary.com/dalnvh4rx/image/upload/v1704052090/medium_DESTACADA_productos_ac46b233c5.png",
                    "hash": "medium_DESTACADA_productos_ac46b233c5",
                    "mime": "image/png",
                    "name": "medium_DESTACADA productos.png",
                    "path": null,
                    "size": 16.43,
                    "width": 750,
                    "height": 750,
                    "provider_metadata": {
                      "public_id": "medium_DESTACADA_productos_ac46b233c5",
                      "resource_type": "image"
                    }
                  },
                  "thumbnail": {
                    "ext": ".png",
                    "url": "https://res.cloudinary.com/dalnvh4rx/image/upload/v1704052090/thumbnail_DESTACADA_productos_ac46b233c5.png",
                    "hash": "thumbnail_DESTACADA_productos_ac46b233c5",
                    "mime": "image/png",
                    "name": "thumbnail_DESTACADA productos.png",
                    "path": null,
                    "size": 3.27,
                    "width": 156,
                    "height": 156,
                    "provider_metadata": {
                      "public_id": "thumbnail_DESTACADA_productos_ac46b233c5",
                      "resource_type": "image"
                    }
                  }
                },
                "hash": "DESTACADA_productos_ac46b233c5",
                "ext": ".png",
                "mime": "image/png",
                "size": 7.11,
                "url": "https://res.cloudinary.com/dalnvh4rx/image/upload/v1704052090/DESTACADA_productos_ac46b233c5.png",
                "previewUrl": null,
                "provider": "cloudinary",
                "provider_metadata": {
                  "public_id": "DESTACADA_productos_ac46b233c5",
                  "resource_type": "image"
                },
                "createdAt": "2023-12-31T19:48:09.835Z",
                "updatedAt": "2023-12-31T19:48:09.835Z"
              }
            }
          ]
        },
        "categories": {
          "data": [
            {
              "id": 6,
              "attributes": {
                "name": "Categoría de prueba 1",
                "createdAt": "2023-12-25T17:38:52.954Z",
                "updatedAt": "2023-12-25T17:38:53.137Z",
                "publishedAt": "2023-12-25T17:38:53.134Z"
              }
            }
          ]
        }
      }
    },
    {
      "id": 2,
      "attributes": {
        "productName": "Esponja de acero",
        "stock": 236,
        "productDescription": "Lorem ipsum dolor sit amet, consectetur adipiscing elit, sed do eiusmod tempor incididunt ut labore et dolore magna aliqua. Ut enim ad minim veniam, quis nostrud exercitation ullamco laboris",
        "productCode": "6515",
        "wholesalePrice": 500,
        "retailPrice": 140,
        "isActive": true,
        "uidProduct": "esponja-de-acero",
        "createdAt": "2023-12-25T20:24:27.904Z",
        "updatedAt": "2024-01-03T21:25:58.229Z",
        "publishedAt": "2023-12-25T20:24:27.892Z",
        "closedBox": 24,
        "productPhoto": {
          "data": [
            {
              "id": 3,
              "attributes": {
                "name": "PUBLICACION CUADRADA aromatizador.png",
                "alternativeText": null,
                "caption": null,
                "width": 1080,
                "height": 1080,
                "formats": {
                  "large": {
                    "ext": ".png",
                    "url": "https://res.cloudinary.com/dalnvh4rx/image/upload/v1703535885/large_PUBLICACION_CUADRADA_aromatizador_e7ee84037a.png",
                    "hash": "large_PUBLICACION_CUADRADA_aromatizador_e7ee84037a",
                    "mime": "image/png",
                    "name": "large_PUBLICACION CUADRADA aromatizador.png",
                    "path": null,
                    "size": 417.74,
                    "width": 1000,
                    "height": 1000,
                    "provider_metadata": {
                      "public_id": "large_PUBLICACION_CUADRADA_aromatizador_e7ee84037a",
                      "resource_type": "image"
                    }
                  },
                  "small": {
                    "ext": ".png",
                    "url": "https://res.cloudinary.com/dalnvh4rx/image/upload/v1703535884/small_PUBLICACION_CUADRADA_aromatizador_e7ee84037a.png",
                    "hash": "small_PUBLICACION_CUADRADA_aromatizador_e7ee84037a",
                    "mime": "image/png",
                    "name": "small_PUBLICACION CUADRADA aromatizador.png",
                    "path": null,
                    "size": 148.41,
                    "width": 500,
                    "height": 500,
                    "provider_metadata": {
                      "public_id": "small_PUBLICACION_CUADRADA_aromatizador_e7ee84037a",
                      "resource_type": "image"
                    }
                  },
                  "medium": {
                    "ext": ".png",
                    "url": "https://res.cloudinary.com/dalnvh4rx/image/upload/v1703535885/medium_PUBLICACION_CUADRADA_aromatizador_e7ee84037a.png",
                    "hash": "medium_PUBLICACION_CUADRADA_aromatizador_e7ee84037a",
                    "mime": "image/png",
                    "name": "medium_PUBLICACION CUADRADA aromatizador.png",
                    "path": null,
                    "size": 272.43,
                    "width": 750,
                    "height": 750,
                    "provider_metadata": {
                      "public_id": "medium_PUBLICACION_CUADRADA_aromatizador_e7ee84037a",
                      "resource_type": "image"
                    }
                  },
                  "thumbnail": {
                    "ext": ".png",
                    "url": "https://res.cloudinary.com/dalnvh4rx/image/upload/v1703535883/thumbnail_PUBLICACION_CUADRADA_aromatizador_e7ee84037a.png",
                    "hash": "thumbnail_PUBLICACION_CUADRADA_aromatizador_e7ee84037a",
                    "mime": "image/png",
                    "name": "thumbnail_PUBLICACION CUADRADA aromatizador.png",
                    "path": null,
                    "size": 23.57,
                    "width": 156,
                    "height": 156,
                    "provider_metadata": {
                      "public_id": "thumbnail_PUBLICACION_CUADRADA_aromatizador_e7ee84037a",
                      "resource_type": "image"
                    }
                  }
                },
                "hash": "PUBLICACION_CUADRADA_aromatizador_e7ee84037a",
                "ext": ".png",
                "mime": "image/png",
                "size": 94.25,
                "url": "https://res.cloudinary.com/dalnvh4rx/image/upload/v1703535884/PUBLICACION_CUADRADA_aromatizador_e7ee84037a.png",
                "previewUrl": null,
                "provider": "cloudinary",
                "provider_metadata": {
                  "public_id": "PUBLICACION_CUADRADA_aromatizador_e7ee84037a",
                  "resource_type": "image"
                },
                "createdAt": "2023-12-25T20:24:44.022Z",
                "updatedAt": "2023-12-25T20:24:44.022Z"
              }
            }
          ]
        },
        "categories": {
          "data": [
            {
              "id": 5,
              "attributes": {
                "name": "Escobas y Escobillones",
                "createdAt": "2023-12-25T17:38:30.907Z",
                "updatedAt": "2023-12-25T17:38:31.616Z",
                "publishedAt": "2023-12-25T17:38:31.610Z"
              }
            }
          ]
        }
      }
    },
    {
      "id": 3,
      "attributes": {
        "productName": "reloj nuevito",
        "stock": 234,
        "productDescription": "Reloj pulsera Skmei 9185 de cuerpo color negro, analógico, fondo negro, con correa de acero color negro, agujas color negro y blanco, dial negro, subesferas color negro, minutero/segundero negro y blanco, bisel color negro y hebilla de gancho",
        "productCode": "1255",
        "wholesalePrice": 23,
        "retailPrice": 601,
        "isActive": true,
        "uidProduct": "reloj-nuevito",
        "createdAt": "2023-12-31T19:47:15.880Z",
        "updatedAt": "2024-01-03T21:26:09.211Z",
        "publishedAt": "2023-12-31T19:47:15.863Z",
        "closedBox": 10,
        "productPhoto": {
          "data": [
            {
              "id": 4,
              "attributes": {
                "name": "DESTACADA HORARIO BLANCO.png",
                "alternativeText": null,
                "caption": null,
                "width": 1080,
                "height": 1080,
                "formats": {
                  "large": {
                    "ext": ".png",
                    "url": "https://res.cloudinary.com/dalnvh4rx/image/upload/v1704052039/large_DESTACADA_HORARIO_BLANCO_efc82d1ac7.png",
                    "hash": "large_DESTACADA_HORARIO_BLANCO_efc82d1ac7",
                    "mime": "image/png",
                    "name": "large_DESTACADA HORARIO BLANCO.png",
                    "path": null,
                    "size": 41.52,
                    "width": 1000,
                    "height": 1000,
                    "provider_metadata": {
                      "public_id": "large_DESTACADA_HORARIO_BLANCO_efc82d1ac7",
                      "resource_type": "image"
                    }
                  },
                  "small": {
                    "ext": ".png",
                    "url": "https://res.cloudinary.com/dalnvh4rx/image/upload/v1704052039/small_DESTACADA_HORARIO_BLANCO_efc82d1ac7.png",
                    "hash": "small_DESTACADA_HORARIO_BLANCO_efc82d1ac7",
                    "mime": "image/png",
                    "name": "small_DESTACADA HORARIO BLANCO.png",
                    "path": null,
                    "size": 18.32,
                    "width": 500,
                    "height": 500,
                    "provider_metadata": {
                      "public_id": "small_DESTACADA_HORARIO_BLANCO_efc82d1ac7",
                      "resource_type": "image"
                    }
                  },
                  "medium": {
                    "ext": ".png",
                    "url": "https://res.cloudinary.com/dalnvh4rx/image/upload/v1704052039/medium_DESTACADA_HORARIO_BLANCO_efc82d1ac7.png",
                    "hash": "medium_DESTACADA_HORARIO_BLANCO_efc82d1ac7",
                    "mime": "image/png",
                    "name": "medium_DESTACADA HORARIO BLANCO.png",
                    "path": null,
                    "size": 29.7,
                    "width": 750,
                    "height": 750,
                    "provider_metadata": {
                      "public_id": "medium_DESTACADA_HORARIO_BLANCO_efc82d1ac7",
                      "resource_type": "image"
                    }
                  },
                  "thumbnail": {
                    "ext": ".png",
                    "url": "https://res.cloudinary.com/dalnvh4rx/image/upload/v1704052038/thumbnail_DESTACADA_HORARIO_BLANCO_efc82d1ac7.png",
                    "hash": "thumbnail_DESTACADA_HORARIO_BLANCO_efc82d1ac7",
                    "mime": "image/png",
                    "name": "thumbnail_DESTACADA HORARIO BLANCO.png",
                    "path": null,
                    "size": 4.16,
                    "width": 156,
                    "height": 156,
                    "provider_metadata": {
                      "public_id": "thumbnail_DESTACADA_HORARIO_BLANCO_efc82d1ac7",
                      "resource_type": "image"
                    }
                  }
                },
                "hash": "DESTACADA_HORARIO_BLANCO_efc82d1ac7",
                "ext": ".png",
                "mime": "image/png",
                "size": 9.02,
                "url": "https://res.cloudinary.com/dalnvh4rx/image/upload/v1704052038/DESTACADA_HORARIO_BLANCO_efc82d1ac7.png",
                "previewUrl": null,
                "provider": "cloudinary",
                "provider_metadata": {
                  "public_id": "DESTACADA_HORARIO_BLANCO_efc82d1ac7",
                  "resource_type": "image"
                },
                "createdAt": "2023-12-31T19:47:18.686Z",
                "updatedAt": "2023-12-31T19:47:18.686Z"
              }
            }
          ]
        },
        "categories": {
          "data": [
            {
              "id": 6,
              "attributes": {
                "name": "Categoría de prueba 1",
                "createdAt": "2023-12-25T17:38:52.954Z",
                "updatedAt": "2023-12-25T17:38:53.137Z",
                "publishedAt": "2023-12-25T17:38:53.134Z"
              }
            }
          ]
        }
      }
    }
  ],
  "meta": {
    "pagination": {
      "page": 1,
      "pageSize": 12,
      "pageCount": 1,
      "total": 4
    }
  }
}
